{
  "slug": "mundo-medicos",
  "titulo": "Mundo: Médicos, por países",
  "subtitulo": "Por 1.000 personas · último dato disponible",
  "categoria": "mundo",
  "fuente": "Fuente: Estadísticas mundiales sobre el personal sanitario de la Organización Mundial de la Salud. Elaboración: Centro de Estudios POPULI · Carlos Aranda.",
  "tags": [
    "mundo",
    "Salud",
    "SH.MED.PHYS.ZS"
  ],
  "fecha": "2026-06-15",
  "tipo": "mapa_mundial",
  "formato": "mundo",
  "imagen": "graficas/mundo-medicos.png",
  "thumb": "thumbs/mundo-medicos.png",
  "datos": null
}